AUTHORS
LICENSE
MANIFEST.in
manage.py
settings.py.sample
setup.py
inhouse/__init__.py
inhouse/admin.py
inhouse/admin_views.py
inhouse/context_processors.py
inhouse/decorators.py
inhouse/filter.py
inhouse/forms.py
inhouse/json.py
inhouse/library.py
inhouse/managers.py
inhouse/middleware.py
inhouse/models.py
inhouse/search_sites.py
inhouse/signals.py
inhouse/urls.py
inhouse/views.py
inhouse/xmlrpc.py
inhouse/fixtures/permissions.json
inhouse/fixtures/test_data.json
inhouse/fixtures/de/initial_data.yaml
inhouse/fixtures/en/initial_data.yaml
inhouse/locale/de/LC_MESSAGES/django.po
inhouse/locale/en/LC_MESSAGES/django.po
inhouse/static/css/admin.css
inhouse/static/css/google.css
inhouse/static/css/handheld.css
inhouse/static/css/style.css
inhouse/static/img/favicon.png
inhouse/static/img/icons.png
inhouse/static/img/logo.png
inhouse/static/js/excanvas.min.js
inhouse/static/js/plugins.js
inhouse/static/js/script.js
inhouse/templates/404.html
inhouse/templates/500.html
inhouse/templates/base.html
inhouse/templates/base_minimal.html
inhouse/templates/booking.html
inhouse/templates/booking_heading.html
inhouse/templates/booking_history.html
inhouse/templates/booking_history_heading.html
inhouse/templates/booking_history_row.html
inhouse/templates/booking_popup.html
inhouse/templates/booking_row.html
inhouse/templates/booking_star.html
inhouse/templates/calendar.html
inhouse/templates/company.html
inhouse/templates/dashboard.html
inhouse/templates/day.html
inhouse/templates/footer.html
inhouse/templates/overview.html
inhouse/templates/overview_booking_heading.html
inhouse/templates/overview_booking_row.html
inhouse/templates/phone_heading.html
inhouse/templates/phone_list.html
inhouse/templates/phone_row.html
inhouse/templates/profile.html
inhouse/templates/project.html
inhouse/templates/project_heading.html
inhouse/templates/project_row.html
inhouse/templates/projects.html
inhouse/templates/starred_booking_heading.html
inhouse/templates/starred_booking_row.html
inhouse_web.egg-info/PKG-INFO
inhouse_web.egg-info/SOURCES.txt
inhouse_web.egg-info/dependency_links.txt
inhouse_web.egg-info/requires.txt
inhouse_web.egg-info/top_level.txt