Metadata-Version: 1.0
Name: inhouse-web
Version: 0.0.4
Summary: Web based time recording and management application
Home-page: http://code.google.com/p/inhouse-web
Author: Henning Kage
Author-email: henning.kage@googlemail.com
License: UNKNOWN
Platform: UNKNOWN
Classifier: Development Status :: 2 - Pre-Alpha
Classifier: Framework :: Django
Classifier: Intended Audience :: Developers
Classifier: License :: OSI Approved :: GNU General Public License (GPL)
Classifier: Natural Language :: English
Classifier: Operating System :: OS Independent
Classifier: Programming Language :: Python
